setup.cfg
setup.py
whoshome.py
whoshome.egg-info/PKG-INFO
whoshome.egg-info/SOURCES.txt
whoshome.egg-info/dependency_links.txt
whoshome.egg-info/entry_points.txt
whoshome.egg-info/requires.txt
whoshome.egg-info/top_level.txt