Metadata-Version: 1.1
Name: whoshome
Version: 1.6.0
Summary: Find out who's home based on Wi-Fi connection
Home-page: https://github.com/fabiocody/Whos-Home
Author: Fabio Codiglioni
Author-email: fabiocody@icloud.com
License: MIT
Keywords: whoshome,wifi,mac,home,arp
Platform: UNKNOWN
Classifier: Programming Language :: Python :: 3.4
Classifier: Programming Language :: Python :: 3.5
